{
  "posts": [],
  "statistics": [
    {
      "id": "1",
      "category": "Web Development",
      "value": 85,
      "unit": "%",
      "date": "2026-01-20",
      "description": "Website performance score"
    },
    {
      "id": "2",
      "category": "Mobile Development",
      "value": 78,
      "unit": "%",
      "date": "2026-01-20",
      "description": "App performance score"
    },
    {
      "id": "3",
      "category": "User Engagement",
      "value": 65,
      "unit": "%",
      "date": "2026-01-20",
      "description": "Average session duration"
    },
    {
      "id": "4",
      "category": "Conversion Rate",
      "value": 4.2,
      "unit": "%",
      "date": "2026-01-20",
      "description": "Overall conversion rate"
    },
    {
      "id": "5",
      "category": "Customer Satisfaction",
      "value": 92,
      "unit": "%",
      "date": "2026-01-20",
      "description": "Net Promoter Score"
    },
    {
      "id": "6",
      "category": "Server Uptime",
      "value": 99.95,
      "unit": "%",
      "date": "2026-01-20",
      "description": "Monthly uptime"
    },
    {
      "id": "7",
      "category": "Page Load Time",
      "value": 1.2,
      "unit": "s",
      "date": "2026-01-20",
      "description": "Average load time"
    },
    {
      "id": "8",
      "category": "Error Rate",
      "value": 0.3,
      "unit": "%",
      "date": "2026-01-20",
      "description": "Error rate per request"
    }
  ],
  
  "goldprices": [
    {
      "id": 1,
      "date": "2024-01-01",
      "price": 2063.50,
      "region": "North America",
      "volume": 1200
    },
    {
      "id": 2,
      "date": "2024-01-02",
      "price": 2071.30,
      "region": "Europe",
      "volume": 980
    },
    {
      "id": 3,
      "date": "2024-01-03",
      "price": 2055.80,
      "region": "Asia",
      "volume": 1500
    },
    {
      "id": 4,
      "date": "2024-01-04",
      "price": 2089.20,
      "region": "North America",
      "volume": 1100
    },
    {
      "id": 5,
      "date": "2024-01-05",
      "price": 2095.60,
      "region": "Europe",
      "volume": 850
    },
    {
      "id": 6,
      "date": "2024-01-06",
      "price": 2102.40,
      "region": "Asia",
      "volume": 1650
    }
  ],

  "cryptocurrencies": []
  
}